jena_com/__init__.py
jena_com/communication.py
jena_com/queries.py
jena_models/__init__.py
jena_models/assignments.py
jena_models/base_solution.py
jena_models/constraints.py
jena_models/dispatcher.py
jena_models/planner.py
jena_models/policies.py
jena_models/set_of_differences.py
jena_models/update_rules.py
jena_reasoning/__init__.py
jena_reasoning/owl.py
jena_sempy-0.9.0.dist-info/LICENSE.txt
jena_sempy-0.9.0.dist-info/METADATA
jena_sempy-0.9.0.dist-info/WHEEL
jena_sempy-0.9.0.dist-info/top_level.txt
jena_sempy-0.9.0.dist-info/RECORD
