Metadata-Version: 2.1
Name: jena-sempy
Version: 0.9.0
Summary: Manipulates semantic information and offers planning capabilities.
Home-page: UNKNOWN
Author: Alexandre Angleraud
Author-email: alexandre.angleraud@tuni.fi
License: New BSD License
Download-URL: https://github.com/Zorrander/jena_sempy/archive/v0.9.0.tar.gz
Platform: UNKNOWN
Requires-Dist: requests
Requires-Dist: rdflib
Requires-Dist: networkx
Requires-Dist: secrets
Requires-Dist: matplotlib (<=2-2-4)
